[
  {
    "collection": "cart",
    "cap": null,
    "index": [
      {"id": -1},
      {"storeId": -1},
      {"createdAt": -1},
      {"id": -1, "storeId": -1},
      {"expiredAt": -1},
      {"orderNumber": -1},
      {"status": -1},
      {"trackId": -1},
      {"cartId": -1},
      {"orderId": -1},
      {"groupId": -1},
      {"currency": -1},
      {"type": -1},
      {"contact.email": -1},
      {"customerEmail": -1},
      {"paymentStatus": -1},
      {"products._id": -1},
      {"products.id": -1},
      {"products.code": -1},
      {"products.createdAt": -1},
      {"products.updatedAt": -1},
      {"products.status": -1},
      {"products.paymentStatus": -1},
      {"products.vendorConfirmationNumber": -1},
      {"products.supplierConfirmationNumber": -1},
      {"products.vendorName": -1},
      {"products.supplierName": -1},
      {"products.type": -1},
      {"products.category": -1},
      {"products.vendorStatus": -1},
      {"products.supplierStatus": -1},
      {"products.valid": -1},
      {"products.isManual": -1},
      {"updatedAt": -1, "_expireAfterSeconds": 345600},
      {"updated_at": -1},
      {"updatedAt": 1, "updated_at": 1}
    ]
  },
  {
    "collection": "customer",
    "cap": null,
    "index": [
      {"updatedAt": -1},
      {"updated_at": -1},
      {"updatedAt": 1, "updated_at": 1}
    ]
  },
  {
    "collection": "coupon",
    "cap": null,
    "index": [
      {"updatedAt": -1},
      {"updated_at": -1},
      {"updatedAt": 1, "updated_at": 1}
    ]
  },
  {
    "collection": "order",
    "cap": null,
    "index": [
      {"id": -1},
      {"cartId": -1},
      {"cartId.$id": -1},
      {"createdAt": -1, "updatedAt": -1},
      {"updated_at": -1},
      {"updatedAt": -1},
      {"type": -1, "createdAt": -1},
      {"paymentStatus": -1, "products.status": -1, "payment.paymentMethod": -1, "isManualOrder": -1, "products.isManual": -1},
      {"additionalData.state": -1, "storeId": -1, "type": -1, "createdAt": -1},
      {"storeId": -1, "type": -1},
      {"additionalData.state": -1, "storeId": -1, "type": -1},
      {"type": -1, "additionalData.state": -1, "createdAt": -1},
      {"type": -1, "paymentStatus": -1, "payment.paymentMethod": -1},
      {"type": -1, "status": -1, "paymentStatus": -1, "payment.paymentMethod": -1, "isManual": -1},
      {"type": -1},
      {"createdAt": -1},
      {"paidAt": -1},
      {"products.status": -1, "products.paymentStatus": -1, "products.options.isFullyMarkedPaid": -1, "products.additionalData.segmentsDetail.markPaidTries": -1, "products.supplierConfirmationNumber": -1, "products.isManual": -1, "products.type": -1, "products.category": -1},
      {"products.type": -1},
      {"products.category": -1},
      {"type": -1, "orderNumber": -1, "paymentStatus": -1, "status": -1, "payment.paymentMethod": -1},
      {"orderNumber": -1, "status": -1, "paymentStatus": -1, "payment.paymentMethod": -1, "isManual": -1, "type": -1, "products.status": -1, "products.type": -1, "products.category": -1},
      {"products.type": -1, "products.status": -1, "products.category": -1},
      {"products.status": -1, "products.paymentStatus": -1, "products.supplierConfirmationNumber": -1, "products.isManual": -1, "products.type": -1, "products.category": -1, "products.id": -1},
      {"products.type": -1, "products.status": -1, "products.paymentStatus": -1, "products.isManual": -1, "products.options.isFullyMarkedPaid": -1, "products.category": -1, "products.id": -1, "products.additionalData.segmentsDetail.markPaidTries": -1},
      {"orderNumber": -1, "type": -1},
      {"orderNumber": -1},
      {"type": -1, "contact.email": -1},
      {"type": -1, "additionalData.headers.x-real-ip": -1},
      {"_id": -1, "paymentStatus": -1, "products.status": -1, "payment.paymentMethod": -1},
      {"trackId": -1},
      {"storeId": -1},
      {"groupId": -1},
      {"groupId": -1, "contact.email": -1, "customerEmail": -1, "additionalData.headers.x-user-email": -1},
      {"contact.email": -1},
      {"products.supplierName": -1, "type": -1},
      {"type": -1, "isManual": -1, "createdAt": -1, "products.category": -1, "products.type": -1, "products.vendorConfirmationNumber": -1, "products.supplierConfirmationNumber": -1, "products.emails.ticket": -1, "products.paymentStatus": -1, "products.status": -1},
      {"customerEmail": -1},
      {"contact.email": -1, "customerEmail": -1, "additionalData.headers.x-user-email": -1},
      {"additionalData.headers.x-user-email": -1},
      {"products.code": -1},
      {"products.category": -1},
      {"updatedAt": 1, "updated_at": 1},
      {"products.options.ahsGroupName": -1, "storeId": -1, "type": -1, "createdAt": -1},
      {"type": -1, "storeId": -1, "products.status": -1, "paymentStatus": -1, "createdAt": -1},
      {"type": -1, "storeId": -1, "products.status": -1, "paymentStatus": -1, "paidAt": -1},
      {"type": -1, "products.vendorConfirmationNumber": -1},
      {"groupId": -1, "type": -1, "products.updatedAt": -1, "products.type": -1, "products.category": -1},
      {"additionalData.headers.x-fp": 1},
      {"additionalData.x-ev-vendorid": 1},
      {"paidAt": -1, "type": -1, "additionalData.bookingMethod": -1, "paymentStatus": -1}
    ]
  },
  {
    "collection": "db_note",
    "cap": null,
    "index": [
      {"createdAt": -1},
      {"orderId": -1},
      {"productId": -1},
      {"orderId": -1, "productId": -1},
      {"orderId": -1, "productId": -1, "createdAt": -1},
      {"orderId": -1, "productId": -1, "createdAt": -1, "updatedAt": -1},
      {"orderId": -1, "productId": -1, "updatedAt": -1},
      {"orderId": -1, "updatedAt": -1},
      {"orderId": -1, "createdAt": -1},
      {"productId": -1, "createdAt": -1},
      {"productId": -1, "updatedAt": -1},
      {"productId.$id": -1, "productId": -1},
      {"orderId.$id": -1, "productId": -1},
      {"orderId.$id": -1, "orderId": -1, "productId": -1, "productId.$id": -1},
      {"updatedAt": -1},
      {"updated_at": -1},
      {"updatedAt": 1, "updated_at": 1}
    ]
  },
  {
    "collection": "order_note",
    "cap": null,
    "index": [
      {"createdAt": -1},
      {"orderId": -1},
      {"productId": -1},
      {"orderId": -1, "productId": -1},
      {"orderId": -1, "productId": -1, "createdAt": -1},
      {"orderId": -1, "productId": -1, "createdAt": -1, "updatedAt": -1},
      {"orderId": -1, "productId": -1, "updatedAt": -1},
      {"orderId": -1, "updatedAt": -1},
      {"orderId": -1, "createdAt": -1},
      {"productId": -1, "createdAt": -1},
      {"productId": -1, "updatedAt": -1},
      {"productId.$id": -1, "productId": -1},
      {"orderId.$id": -1, "productId": -1},
      {"orderId.$id": -1, "orderId": -1, "productId": -1, "productId.$id": -1},
      {"updatedAt": -1},
      {"updated_at": -1},
      {"updatedAt": 1, "updated_at": 1}
    ]
  },
  {
    "collection": "price_rule",
    "cap": null,
    "index": [
      {"is_active": -1, "product_type": -1, "is_deleted": -1, "to_date": -1, "from_date": -1, "app_id": -1},
      {"is_active": -1, "product_type": -1, "is_deleted": -1, "to_date": -1, "from_date": -1, "app_id": -1, "action.currency": -1, "priority": -1},
      {"is_deleted": -1, "created_at": -1},
      {"is_active": -1, "product_type": -1, "is_deleted": -1, "to_date": -1, "from_date": -1, "app_id": -1, "coupon": -1},
      {"is_deleted": -1, "coupon": -1},
      {"coupon": -1, "is_deleted": -1, "priority": -1},
      {"_id": -1, "is_active": -1},
      {"_id": -1, "is_active": -1, "product_type": -1},
      {"product_type": -1},
      {"is_active": -1},
      {"priority": -1},
      {"coupon": -1},
      {"from_date": -1},
      {"to_date": -1},
      {"stop": -1},
      {"app_id": -1},
      {"is_deleted": -1},
      {"disable_coupons": -1},
      {"arr_date": -1},
      {"dep_date": -1},
      {"created_at": -1},
      {"code": -1},
      {"email": 1},
      {"updatedAt": -1},
      {"updated_at": -1},
      {"updatedAt": 1, "updated_at": 1}
    ]
  },
  {
    "collection": "price_rule_coupon",
    "cap": null,
    "index": [
      {"is_deleted": -1, "created_at": -1},
      {"is_active": -1, "product_type": -1, "is_deleted": -1, "to_date": -1, "from_date": -1, "app_id": -1, "coupon": -1},
      {"coupon": -1, "is_deleted": -1},
      {"coupon": -1, "is_deleted": -1, "priority": -1},
      {"_id": -1, "is_active": -1},
      {"_id": -1, "is_active": -1, "product_type": -1},
      {"product_type": -1},
      {"is_active": -1},
      {"priority": -1},
      {"coupon": -1},
      {"from_date": -1},
      {"to_date": -1},
      {"stop": -1},
      {"app_id": -1},
      {"is_deleted": -1},
      {"disable_coupons": -1},
      {"arr_date": -1},
      {"dep_date": -1},
      {"created_at": -1},
      {"code": -1},
      {"email": 1},
      {"is_active": 1, "product_type": 1, "is_deleted": 1, "to_date": 1, "from_date": 1, "app_id": 1},
      {"updatedAt": -1},
      {"updated_at": -1},
      {"updatedAt": 1, "updated_at": 1}
    ]
  }
]